ley/__init__.py
ley/ley.py
ley-0.1.0.dist-info/LICENSE
ley-0.1.0.dist-info/WHEEL
ley-0.1.0.dist-info/METADATA
ley-0.1.0.dist-info/RECORD
