Metadata-Version: 2.1
Name: ley
Version: 0.1.0
Summary: A package for communicating with the Citadel backend.
License: MIT
Author: Miles van der Lely
Author-email: milesvanderlely@gmail.com
Requires-Python: >=3.9,<4.0
Classifier: License :: OSI Approved :: MIT License
Classifier: Programming Language :: Python :: 3
Classifier: Programming Language :: Python :: 3.9
Classifier: Programming Language :: Python :: 3.10
Classifier: Programming Language :: Python :: 3.11
Requires-Dist: jsonschema (>=4.17.0,<5.0.0)
Requires-Dist: websockets (>=10.4,<11.0)
